colordict/__init__.py
colordict/backup.json
colordict/cdict.py
colordict/general.py
colordict/gradients.py
colordict/palettes/CSS.json
colordict/palettes/fluorescent.json
colordict/palettes/gem_tones.json
colordict/palettes/heads_n_tails.json
colordict/palettes/independent.json
colordict/palettes/magic_scent.json
colordict/palettes/metallic_fx.json
colordict/palettes/mystic_forest.json
colordict/palettes/rainbow.json
colordict/palettes/silly_scents.json
colordict/palettes/silver_swirls.json
colordict/palettes/world_flags.json
colordict-1.2.6.dist-info/LICENSE.txt
colordict-1.2.6.dist-info/METADATA
colordict-1.2.6.dist-info/WHEEL
colordict-1.2.6.dist-info/top_level.txt
colordict-1.2.6.dist-info/RECORD
