Metadata-Version: 2.1
Name: colordict
Version: 1.2.6
Summary: A package to allow for easy maintenance of a color dictionary with palettes, so you can use the colors that you like in your different projects.
Home-page: https://github.com/aleferna12/colordict
Author: aleferna
License: MIT
Platform: UNKNOWN
License-File: LICENSE.txt
